timeframe/__init__.py
timeframe/timeframe.py
timeframe_event-1.1.8.dist-info/LICENSE
timeframe_event-1.1.8.dist-info/METADATA
timeframe_event-1.1.8.dist-info/WHEEL
timeframe_event-1.1.8.dist-info/RECORD
