Metadata-Version: 2.1
Name: timeframe-event
Version: 1.1.8
Summary: Python timeframe tool for time monitoring for each event, error handling, traceback recording...
Home-page: https://github.com/i-am-unknown-81514525/timeframe/tree/main
Author: i-am-unknown
Author-email: iamaunknownpeople@protonmail.com
Requires-Python: >=3.6,<4.0
Classifier: License :: OSI Approved :: GNU General Public License v3 (GPLv3)
Classifier: Operating System :: OS Independent
Classifier: Programming Language :: Python :: 3
Classifier: Programming Language :: Python :: 3.6
Classifier: Programming Language :: Python :: 3.7
Classifier: Programming Language :: Python :: 3.8
Classifier: Programming Language :: Python :: 3.9
Classifier: Programming Language :: Python :: 3.10
Classifier: Programming Language :: Python :: 3.11
Classifier: Programming Language :: Python :: 3.12
Project-URL: Repository, https://github.com/i-am-unknown-81514525/timeframe/tree/main
